cool_open_client/__init__.py
cool_open_client/cool_automation_client.py
cool_open_client/hvac_units_factory.py
cool_open_client/unit.py
cool_open_client/client/__init__.py
cool_open_client/client/api_client.py
cool_open_client/client/api_response.py
cool_open_client/client/configuration.py
cool_open_client/client/exceptions.py
cool_open_client/client/py.typed
cool_open_client/client/rest.py
cool_open_client/client/api/__init__.py
cool_open_client/client/api/authentication_api.py
cool_open_client/client/api/customer_api.py
cool_open_client/client/api/customer_sites_api.py
cool_open_client/client/api/customer_users_api.py
cool_open_client/client/api/customers_api.py
cool_open_client/client/api/device_api.py
cool_open_client/client/api/device_units_api.py
cool_open_client/client/api/devices_api.py
cool_open_client/client/api/me_api.py
cool_open_client/client/api/services_api.py
cool_open_client/client/api/site_api.py
cool_open_client/client/api/site_systems_api.py
cool_open_client/client/api/site_users_api.py
cool_open_client/client/api/sites_api.py
cool_open_client/client/api/system_api.py
cool_open_client/client/api/system_control_api.py
cool_open_client/client/api/system_units_api.py
cool_open_client/client/api/systems_api.py
cool_open_client/client/api/unit_api.py
cool_open_client/client/api/unit_control_api.py
cool_open_client/client/api/units_api.py
cool_open_client/client/api/user_api.py
cool_open_client/client/api/users_api.py
cool_open_client/client/api/websocket_api.py
cool_open_client/client/models/__init__.py
cool_open_client/client/models/authenticate_request_body.py
cool_open_client/client/models/bad_response401.py
cool_open_client/client/models/bad_response403.py
cool_open_client/client/models/bad_response404.py
cool_open_client/client/models/bad_response500.py
cool_open_client/client/models/control_tree_response.py
cool_open_client/client/models/control_tree_response_data.py
cool_open_client/client/models/control_tree_response_data_customers.py
cool_open_client-0.0.18.dist-info/licenses/LICENSE.md
cool_open_client-0.0.18.dist-info/METADATA
cool_open_client-0.0.18.dist-info/WHEEL
cool_open_client-0.0.18.dist-info/top_level.txt
cool_open_client-0.0.18.dist-info/RECORD
