Metadata-Version: 2.4
Name: cool-open-client
Version: 0.0.18
Summary: This library will enable the use of the CoolAutomation API by third party projects
Home-page: https://github.com/ShayGus/CoolControlOpenClient
Author: Shay Gus
Author-email: sgusin@gmail.com
License: GPLv3+
Classifier: Programming Language :: Python :: 3.9
Classifier: License :: OSI Approved :: GNU General Public License v3 or later (GPLv3+)
Classifier: Operating System :: OS Independent
Classifier: Intended Audience :: Developers
Classifier: Natural Language :: English
Requires-Python: >=3.9
License-File: LICENSE.md
Requires-Dist: certifi>=14.05.14
Requires-Dist: six>=1.10
Requires-Dist: python_dateutil>=2.5.3
Requires-Dist: urllib3>=1.15.1
Requires-Dist: bidict==0.23.0
Requires-Dist: rel>=0.4.7
Requires-Dist: websocket-client>=1.3.3
Requires-Dist: marshmallow>=3.17.0
Requires-Dist: marshmallow-dataclass>=8.5.8
Requires-Dist: typeguard>=2.13.3
Requires-Dist: aiohttp>=3.8.1
Requires-Dist: websockets>=10.3
Requires-Dist: pydantic>=2.11.9
Requires-Dist: aiohttp_retry>=2.9.1
Dynamic: author
Dynamic: author-email
Dynamic: classifier
Dynamic: description
Dynamic: description-content-type
Dynamic: home-page
Dynamic: license
Dynamic: license-file
Dynamic: requires-dist
Dynamic: requires-python
Dynamic: summary
